power_nudge/__init__.py
power_nudge/config.py
power_nudge/main.py
power_nudge/settings.toml
power_nudge/utils/helper.py
power_nudge/utils/logger.py
power_nudge-0.2.2.dist-info/LICENSE
power_nudge-0.2.2.dist-info/METADATA
power_nudge-0.2.2.dist-info/WHEEL
power_nudge-0.2.2.dist-info/RECORD
