Metadata-Version: 2.3
Name: power-nudge
Version: 0.2.2
Summary: A macOS utility that alerts you via WhatsApp when your battery reaches a defined threshold using Twilio.
License: MIT
Keywords: battery,twilio,macos,whatsapp,automation,notification
Author: Lav Sharma
Author-email: lavsharma2016@gmail.com
Requires-Python: >=3.12,<4.0
Classifier: Development Status :: 3 - Alpha
Classifier: Intended Audience :: End Users/Desktop
Classifier: License :: OSI Approved :: MIT License
Classifier: Operating System :: MacOS
Classifier: Programming Language :: Python :: 3.12
Classifier: Topic :: Utilities
Classifier: Topic :: Communications :: Chat
Requires-Dist: dynaconf (>=3.2.10,<4.0.0)
Requires-Dist: loguru (>=0.7.3,<0.8.0)
Requires-Dist: twilio-helper (>=0.1.0,<0.2.0)
